devclean/__init__.py
devclean/__main__.py
devclean/cleaners.py
devclean/cli.py
devclean/core.py
devclean/formatters.py
devclean/utils.py
devclean-1.0.36.dist-info/METADATA
devclean-1.0.36.dist-info/WHEEL
devclean-1.0.36.dist-info/entry_points.txt
devclean-1.0.36.dist-info/top_level.txt
devclean-1.0.36.dist-info/RECORD
