Metadata-Version: 2.4
Name: devclean
Version: 1.0.36
Summary: CLI tool to strip comments and file formatting safely.
Author-email: appsfolder <axelixdev@gmail.com>
License: MIT
Project-URL: Homepage, https://github.com/appsfolder/devclean
Project-URL: Repository, https://github.com/appsfolder/devclean
Project-URL: Issues, https://github.com/appsfolder/devclean/issues
Keywords: devclean,cleanup,refactoring,comments,formatter,minifier
Classifier: Programming Language :: Python :: 3
Classifier: License :: OSI Approved :: MIT License
Classifier: Operating System :: OS Independent
Classifier: Topic :: Software Development :: Quality Assurance
Classifier: Topic :: Utilities
Classifier: Intended Audience :: Developers
Requires-Python: >=3.7
